{
  "project_info": {
    "project_number": "710645981730",
    "project_id": "teamcenter-player",
    "storage_bucket": "teamcenter-player.appspot.com"
  },
  "client": [
    {
      "client_info": {
        "mobilesdk_app_id": "1:710645981730:android:39feb5bec08c6aea42207b",
        "android_client_info": {
          "package_name": "com.shtibel.teamcenter_player"
        }
      },
      "oauth_client": [
        {
          "client_id": "710645981730-knlfo19qpbou4oc29bq578o0cni4f912.apps.googleusercontent.com",
          "client_type": 1,
          "android_info": {
            "package_name": "com.shtibel.teamcenter_player",
            "certificate_hash": "22ad693521df34415517b3b16f5101d0eda869e1"
          }
        },
        {
          "client_id": "710645981730-quief7o56rgclqvaohdq12rt227pe9od.apps.googleusercontent.com",
          "client_type": 3
        }
      ],
      "api_key": [
        {
          "current_key": "AIzaSyDkXvgzb1w0XHIVryVH4NhroCn5DKg_1dk"
        }
      ],
      "services": {
        "appinvite_service": {
          "other_platform_oauth_client": [
            {
              "client_id": "710645981730-quief7o56rgclqvaohdq12rt227pe9od.apps.googleusercontent.com",
              "client_type": 3
            }
          ]
        }
      }
    }
  ],
  "configuration_version": "1"
}